youtube_mcp/__init__.py
youtube_mcp/core.py
youtube_mcp/main.py
youtube_mcp-0.1.1.dist-info/METADATA
youtube_mcp-0.1.1.dist-info/WHEEL
youtube_mcp-0.1.1.dist-info/entry_points.txt
youtube_mcp-0.1.1.dist-info/licenses/LICENSE
youtube_mcp-0.1.1.dist-info/RECORD
