Metadata-Version: 2.4
Name: youtube-mcp
Version: 0.1.1
Summary: MCP для загрузки транскрипций YouTube видео
Project-URL: Homepage, https://github.com/yourusername/youtube-mcp
Project-URL: Bug Tracker, https://github.com/yourusername/youtube-mcp/issues
Author-email: Nikita Panferov <nikpanfer@gmail.com>
License: MIT
License-File: LICENSE
Classifier: License :: OSI Approved :: MIT License
Classifier: Operating System :: OS Independent
Classifier: Programming Language :: Python :: 3
Requires-Python: >=3.13
Requires-Dist: build>=1.2.2.post1
Requires-Dist: mcp[cli]>=1.1.3
Requires-Dist: twine>=6.1.0
Requires-Dist: youtube-transcript-api>=0.6.0
